btcrs-0.0.1.dist-info/METADATA
btcrs-0.0.1.dist-info/WHEEL
btcrs/__init__.py
btcrs/btcrs.cpython-310-x86_64-linux-gnu.so
btcrs-0.0.1.dist-info/RECORD
